deltawoot/__init__.py
deltawoot/avatar.jpg
deltawoot/recv.py
deltawoot/send.py
deltawoot/woot.py
deltawoot-1.3.1.dist-info/LICENSE
deltawoot-1.3.1.dist-info/METADATA
deltawoot-1.3.1.dist-info/WHEEL
deltawoot-1.3.1.dist-info/entry_points.txt
deltawoot-1.3.1.dist-info/top_level.txt
deltawoot-1.3.1.dist-info/RECORD
