Metadata-Version: 2.1
Name: deltawoot
Version: 1.3.1
Summary: A deltachat client for chatwoot, so users can talk to chatwoot encrypted.
Home-page: https://github.com/deltachat-bot/deltawoot
Author: missytake
Author-email: missytake@systemli.org
Project-URL: Bug Tracker, https://github.com/deltachat-bot/deltawoot/issues
Classifier: Programming Language :: Python :: 3
Classifier: License :: OSI Approved :: ISC License (ISCL)
Classifier: Operating System :: OS Independent
Requires-Python: >=3.10
License-File: LICENSE
Requires-Dist: deltachat-rpc-client
Requires-Dist: deltachat-rpc-server
Requires-Dist: ConfigArgParse
Requires-Dist: requests
Requires-Dist: flask
Requires-Dist: sentry-sdk[flask]
Provides-Extra: dev
Requires-Dist: pytest; extra == "dev"
Requires-Dist: pytest-timeout; extra == "dev"
